double_debias/__init__.py
double_debias/double_debias.py
double_debias/tests/__init__.py
double_debias/tests/code_run_test.py
double_debias-0.0.5.dist-info/LICENSE
double_debias-0.0.5.dist-info/METADATA
double_debias-0.0.5.dist-info/WHEEL
double_debias-0.0.5.dist-info/top_level.txt
double_debias-0.0.5.dist-info/RECORD
