Metadata-Version: 2.1
Name: double-debias
Version: 0.0.5
Summary: Implements Double Debias Estimator
Home-page: https://github.com/joe5saia/double_debias
Author: Joe Saia
Author-email: joe5saia@gmail.com
License: UNKNOWN
Platform: UNKNOWN
Classifier: Programming Language :: Python :: 3
Classifier: License :: OSI Approved :: MIT License
Classifier: Operating System :: OS Independent
Requires-Python: >=3.6
Requires-Dist: numpy
Requires-Dist: sklearn
